chibi_wrapper/__init__.py
chibi_wrapper/chibi_wrapper.py
python_chibisafe-0.1.1.dist-info/METADATA
python_chibisafe-0.1.1.dist-info/WHEEL
python_chibisafe-0.1.1.dist-info/top_level.txt
python_chibisafe-0.1.1.dist-info/RECORD
